{
  "entity": "patients",
  "indexes": [
    { "component": "IndexButton","text": "Lace", "criterion": "tertile" },
    { "component": "IndexButton", "text": "Charlston", "criterion": "quartile" },
    { "component": "IndexButton", "text": "ASA", "criterion": "patients[.asa == 'I']" },
    { "component": "IndexButton", "text": "GMA", "criterion": "patients[.gma > 0]" },
    { "component": "IndexButton", "text": "Barthel", "criterion": "tertile" }
  ],
  "values": [
    { "text": "Name", "value": "firstName" },
    { "text": "Surname", "value": "lastName" },
    { "text": "Retrieval", "value": "retrieval" },
    { "text": "Selfcare", "value": "selfcare" },
    { "text": "Dwelling", "value": "dwelling" },
    { "text": "Career", "value": "career" },
    { "text": "LACE", "value": "lace" },
    { "text": "Charlson", "value": "charlson" },
    { "text": "Barthel", "value": "barthel" },
    { "text": "ASA", "value": "asa" },
    { "text": "GMA", "value": "gma" }
  ],
  "fences": [
    { "component":"FenceTextArea", "id": "Fence 1", "lat": "39.997", "lng": "116.322", "radius": "500" },
    { "component":"FenceTextArea", "id": "Fence 2", "lat": "40.006", "lng": "116.325", "radius": "500" },
    { "component":"FenceTextArea", "id": "Fence 3", "lat": "40.002", "lng": "116.322", "radius": "500" },
    { "component":"FenceTextArea", "id": "Fence 4", "lat": "40.007", "lng": "116.319", "radius": "500" }
  ]
}
